vnpy/__init__.py
vnpy/alpha/__init__.py
vnpy/alpha/lab.py
vnpy/alpha/logger.py
vnpy/alpha/dataset/__init__.py
vnpy/alpha/dataset/cs_function.py
vnpy/alpha/dataset/processor.py
vnpy/alpha/dataset/ta_function.py
vnpy/alpha/dataset/template.py
vnpy/alpha/dataset/ts_function.py
vnpy/alpha/dataset/utility.py
vnpy/alpha/dataset/datasets/__init__.py
vnpy/alpha/dataset/datasets/alpha_158.py
vnpy/alpha/model/__init__.py
vnpy/alpha/model/template.py
vnpy/alpha/model/models/__init__.py
vnpy/alpha/model/models/lasso_model.py
vnpy/alpha/model/models/lgb_model.py
vnpy/alpha/model/models/mlp_model.py
vnpy/alpha/strategy/__init__.py
vnpy/alpha/strategy/backtesting.py
vnpy/alpha/strategy/template.py
vnpy/alpha/strategy/strategies/__init__.py
vnpy/alpha/strategy/strategies/equity_demo_strategy.py
vnpy/chart/__init__.py
vnpy/chart/axis.py
vnpy/chart/base.py
vnpy/chart/item.py
vnpy/chart/manager.py
vnpy/chart/widget.py
vnpy/event/__init__.py
vnpy/event/engine.py
vnpy/rpc/__init__.py
vnpy/rpc/client.py
vnpy/rpc/common.py
vnpy/rpc/server.py
vnpy/trader/__init__.py
vnpy/trader/app.py
vnpy/trader/constant.py
vnpy/trader/converter.py
vnpy/trader/database.py
vnpy/trader/datafeed.py
vnpy/trader/engine.py
vnpy/trader/event.py
vnpy/trader/gateway.py
vnpy/trader/logger.py
vnpy/trader/object.py
vnpy/trader/optimize.py
vnpy/trader/setting.py
vnpy/trader/utility.py
vnpy/trader/locale/__init__.py
vnpy/trader/locale/build_hook.py
vnpy/trader/locale/generate_mo.bat
vnpy/trader/locale/generate_pot.bat
vnpy/trader/locale/vnpy.pot
vnpy/trader/locale/en/LC_MESSAGES/vnpy.po
vnpy/trader/ui/__init__.py
vnpy/trader/ui/mainwindow.py
vnpy/trader/ui/qt.py
vnpy/trader/ui/widget.py
vnpy/trader/ui/ico/__init__.py
vnpy/trader/ui/ico/about.ico
vnpy/trader/ui/ico/connect.ico
vnpy/trader/ui/ico/contract.ico
vnpy/trader/ui/ico/database.ico
vnpy/trader/ui/ico/editor.ico
vnpy/trader/ui/ico/email.ico
vnpy/trader/ui/ico/exit.ico
vnpy/trader/ui/ico/forum.ico
vnpy/trader/ui/ico/restore.ico
vnpy/trader/ui/ico/test.ico
vnpy-4.1.0.dist-info/METADATA
vnpy-4.1.0.dist-info/WHEEL
vnpy-4.1.0.dist-info/licenses/LICENSE
vnpy-4.1.0.dist-info/RECORD
